{
    "created_time": "2019-06-02T00:44:18Z",
    "files": [
        {
            "attachment_folder": "",
            "attachments": [
            ],
            "created_time": "2019-06-02T00:44:18Z",
            "modified_time": "2019-06-02T00:44:18Z",
            "name": "尼采的锤子内容预告.md",
            "tags": [
            ]
        },
        {
            "attachment_folder": "",
            "attachments": [
            ],
            "created_time": "2019-06-02T00:44:18Z",
            "modified_time": "2019-06-02T00:44:18Z",
            "name": "泰利斯的井.md",
            "tags": [
            ]
        },
        {
            "attachment_folder": "",
            "attachments": [
            ],
            "created_time": "2019-06-08T16:27:15Z",
            "modified_time": "2019-06-08T16:27:30Z",
            "name": "普罗泰格拉和猪.md",
            "tags": [
            ]
        },
        {
            "attachment_folder": "",
            "attachments": [
            ],
            "created_time": "2019-06-28T14:51:21Z",
            "modified_time": "2019-06-28T14:52:55Z",
            "name": "柏拉图的洞穴.md",
            "tags": [
            ]
        },
        {
            "attachment_folder": "",
            "attachments": [
            ],
            "created_time": "2019-06-28T14:51:30Z",
            "modified_time": "2019-06-28T14:53:19Z",
            "name": "苏格拉底的探问.md",
            "tags": [
            ]
        },
        {
            "attachment_folder": "",
            "attachments": [
            ],
            "created_time": "2019-06-28T14:54:12Z",
            "modified_time": "2019-06-28T14:54:50Z",
            "name": "之诺和乌龟.md",
            "tags": [
            ]
        }
    ],
    "sub_directories": [
    ],
    "version": "1"
}
